setup.cfg
setup.py
bulatProject.egg-info/PKG-INFO
bulatProject.egg-info/SOURCES.txt
bulatProject.egg-info/dependency_links.txt
bulatProject.egg-info/top_level.txt
pythonProject/__init__.py
pythonProject/functions.py