Metadata-Version: 2.1
Name: bulatProject
Version: 0.0.1
Summary: A useful module
Author: gbu1at
Author-email: bulatchess@mail.ru
